costo/__init__.py
costo/connectors.py
costo/coupled_BC.py
costo/coupling.py
costo/couplingData.py
costo/mesh.py
costo/neibor.py
costo/pipeline.py
costo/scheduler.py
costo/timeManager.py
costo/utils.py
costo-0.0.9.data/scripts/set_costo_env
costo-0.0.9.dist-info/licenses/LICENSE
costo-0.0.9.dist-info/METADATA
costo-0.0.9.dist-info/WHEEL
costo-0.0.9.dist-info/top_level.txt
costo-0.0.9.dist-info/RECORD
