Metadata-Version: 2.4
Name: costo
Version: 0.0.9
Summary: COSTO stands for COSimulation TOols
Author-email: teddy Chantrait <teddy.chantrait@gmail.com>
Maintainer-email: teddy Chantrait <teddy.chantrait@gmail.com>
License:                     GNU GENERAL PUBLIC LICENSE
Project-URL: Homepage, https://gitlab.com/Te_ch/costo
Project-URL: Documentation, https://te_ch.gitlab.io/costo
Project-URL: Repository, https://gitlab.com/Te_ch/costo.git
Classifier: Development Status :: 4 - Beta
Classifier: License :: OSI Approved :: GNU General Public License v3 (GPLv3)
Classifier: Programming Language :: Python :: 3 :: Only
Classifier: Programming Language :: Python :: 3.10
Classifier: Programming Language :: Python :: 3.11
Classifier: Programming Language :: Python :: 3.12
Requires-Python: >=3.10
License-File: LICENSE
Requires-Dist: mpi4py>=4.0.3
Requires-Dist: cython>=3.0.11
Requires-Dist: numpy>=2.2
Requires-Dist: colorama>=0.4.4
Requires-Dist: pyvista>=0.44.2
Requires-Dist: scipy>=1.15
Requires-Dist: mgmetis>=0.1.1
Provides-Extra: test
Requires-Dist: pytest>=8.3.3; extra == "test"
Requires-Dist: nonRegressionTestTools>=1.1.6; extra == "test"
Provides-Extra: dev
Requires-Dist: coverage>=7.6.1; extra == "dev"
Requires-Dist: hypothesis; extra == "dev"
Requires-Dist: sphinx; extra == "dev"
Requires-Dist: ansi2html>=1.7.0; extra == "dev"
Requires-Dist: sphinxcontrib-programoutput>=0.17; extra == "dev"
Requires-Dist: sphinx-rtd-theme>=2.0.0; extra == "dev"
Requires-Dist: build>=1.2.1; extra == "dev"
Requires-Dist: twine>=5.1.1; extra == "dev"
Dynamic: license-file
